{
  "page_type": "project_details",
  "slug": "binghatti-flare",
  "id": null,
  "developer": "Binghatti",
  "brand": null,
  "country": {
    "ar": "الإمارات العربية المتحدة",
    "en": "United Arab Emirates"
  },
  "city": {
    "ar": null,
    "en": "Dubai"
  },
  "area": {
    "ar": null,
    "en": "Jumeirah Village Triangle"
  },
  "location": {
    "ar": null,
    "en": "Jumeirah Village Triangle",
    "country": {
      "en": "United Arab Emirates",
      "ar": "الإمارات العربية المتحدة"
    },
    "city": {
      "en": "Dubai",
      "ar": "دبي"
    },
    "area": {
      "ar": null,
      "en": "Jumeirah Village Triangle"
    }
  },
  "latitude": 25.018834826093297,
  "longitude": 55.04598751442834,
  "mapDescription": {
    "ar": null,
    "en": null
  },
  "mapPointsOfInterest": [],
  "projectCategory": null,
  "projectName": {
    "ar": null,
    "en": "Binghatti Flare"
  },
  "summary": {
    "ar": null,
    "en": null
  },
  "heroCopy": {
    "ar": {
      "title": null,
      "subtitle": null
    },
    "en": {
      "title": null,
      "subtitle": null
    }
  },
  "description": {
    "ar": null,
    "en": "Experinece Binghatti Flare, Jumeirah Village Triangle. A premium residential project offering modern living in a prime family-friendly location."
  },
  "propertyTypes": [
    {
      "ar": null,
      "en": "Apartment"
    }
  ],
  "bedrooms": [
    0,
    1,
    2,
    3,
    4
  ],
  "propertyTypeLinks": [],
  "paymentPlan": {
    "ar": null,
    "en": "payment plan, which is 70/30:"
  },
  "minAreaSqft": 1553,
  "maxAreaSqft": 1553,
  "minAreaSqmt": 144,
  "maxAreaSqmt": 144,
  "minPriceAED": 800000,
  "maxPriceAED": null,
  "deliveryDate": "Q2 2027",
  "launchDate": null,
  "projectStatus": {
    "ar": "تحت الإنشاء",
    "en": "Under Construction"
  },
  "views": [],
  "goldenVisaEligible": null,
  "3D_TourLink": null,
  "brochurePdfLink": {
    "ar": null,
    "en": "https://binghatti-public.s3.me-central-1.amazonaws.com/project-assets/binghatti-flare-assets/binghatti-flare-digital-brochure.pdf"
  },
  "videoLink": "https://www.youtube.com/watch?v=DwBk6wGQx88",
  "heroImage": "https://binghattiweb.imgix.net/binghatti-flare-hero-banner.webp?auto=format,compress&q=75",
  "galleryImages": [
    "https://binghattiweb.imgix.net/binghatti-flare-hero-banner.webp?auto=format,compress&q=75",
    "https://binghattiweb.imgix.net/binghatti-flare-amenities-1.webp",
    "https://binghattiweb.imgix.net/binghatti-flare-amenities-2.webp",
    "https://binghattiweb.imgix.net/binghatti-flare-amenities-3.webp",
    "https://binghattiweb.imgix.net/binghatti-flare-amenities-1.webp?auto=format,compress,dpr&fit=max&w=1000&h=700&q=75",
    "https://binghattiweb.imgix.net/binghatti-flare-amenities-2.webp?auto=format,compress,dpr&fit=max&w=1000&h=700&q=75",
    "https://binghattiweb.imgix.net/binghatti-flare-amenities-3.webp?auto=format,compress,dpr&fit=max&w=1000&h=700&q=75",
    "https://binghattiweb.imgix.net/binghatti-flare-studio-layout-1.webp",
    "https://binghattiweb.imgix.net/binghatti-flare-01-one-bedroom-layout.webp",
    "https://binghattiweb.imgix.net/binghatti-flare-01-two-bedroom-layout.webp",
    "https://binghattiweb.imgix.net/binghatti-flare-01-three-bedroom-layout.webp",
    "https://binghattiweb.imgix.net/binghatti-flare-01-four-bedroom-layout.webp",
    "https://binghattiweb.imgix.net/bedroom-img.webp",
    "https://binghattiweb.imgix.net/binghatti-flare-02-4.webp",
    "https://binghattiweb.imgix.net/binghatti-flare-footer.webp"
  ],
  "amenities": [
    {
      "name": {
        "ar": null,
        "en": "Swimming Pool"
      },
      "description": {
        "ar": null,
        "en": null
      }
    },
    {
      "name": {
        "ar": null,
        "en": "Fitness Facilities"
      },
      "description": {
        "ar": null,
        "en": null
      }
    },
    {
      "name": {
        "ar": null,
        "en": "Landscaped Outdoor Areas"
      },
      "description": {
        "ar": null,
        "en": null
      }
    },
    {
      "name": {
        "ar": null,
        "en": "Family-friendly Spaces"
      },
      "description": {
        "ar": null,
        "en": null
      }
    }
  ],
  "highlights": [
    {
      "ar": null,
      "en": "Modern apartments in Jumeirah Village Triangle"
    },
    {
      "ar": null,
      "en": "Prime family-friendly location"
    },
    {
      "ar": null,
      "en": "Studio, 1, 2, 3 & 4 bedroom apartments available"
    },
    {
      "ar": null,
      "en": "Premium residential project"
    }
  ],
  "insights": {
    "ar": null,
    "en": null
  },
  "projectPageLink": "https://www.binghatti.com/en/projects/binghatti-flare",
  "contact": {
    "phone": "+97180015",
    "whatsapp": "+97180015",
    "email": "SALES@BINGHATTI.COM"
  },
  "meta": {
    "sourceAnalyzed": "RAW_HTML_PROVIDED",
    "fetchedAt": "2025-11-09T18:05:13.221Z",
    "title": "Binghatti Flare – Studio, 1,2 ,3, & 4 BR Apartments in JVT",
    "description": "Experinece Binghatti Flare, Jumeirah Village Triangle. A premium residential project offering modern living in a prime family-friendly location.",
    "canonical": "https://www.binghatti.com/en/projects/binghatti-flare"
  },
  "assets": {
    "images": [
      "https://binghattiweb.imgix.net/binghatti-flare-hero-banner.webp?auto=format,compress&q=75",
      "https://binghattiweb.imgix.net/binghatti-flare-amenities-1.webp",
      "https://binghattiweb.imgix.net/binghatti-flare-amenities-2.webp",
      "https://binghattiweb.imgix.net/binghatti-flare-amenities-3.webp",
      "https://binghattiweb.imgix.net/binghatti-flare-amenities-1.webp?auto=format,compress,dpr&fit=max&w=1000&h=700&q=75",
      "https://binghattiweb.imgix.net/binghatti-flare-amenities-2.webp?auto=format,compress,dpr&fit=max&w=1000&h=700&q=75",
      "https://binghattiweb.imgix.net/binghatti-flare-amenities-3.webp?auto=format,compress,dpr&fit=max&w=1000&h=700&q=75",
      "https://binghattiweb.imgix.net/binghatti-flare-studio-layout-1.webp",
      "https://binghattiweb.imgix.net/binghatti-flare-01-one-bedroom-layout.webp",
      "https://binghattiweb.imgix.net/binghatti-flare-01-two-bedroom-layout.webp",
      "https://binghattiweb.imgix.net/binghatti-flare-01-three-bedroom-layout.webp",
      "https://binghattiweb.imgix.net/binghatti-flare-01-four-bedroom-layout.webp",
      "https://binghattiweb.imgix.net/bedroom-img.webp",
      "https://binghattiweb.imgix.net/binghatti-flare-02-4.webp",
      "https://binghattiweb.imgix.net/binghatti-flare-footer.webp"
    ],
    "videos": [],
    "pdfs": [
      "https://binghatti-public.s3.me-central-1.amazonaws.com/project-assets/binghatti-flare-assets/binghatti-flare-digital-brochure.pdf",
      "https://binghatti-public.s3.me-central-1.amazonaws.com/project-assets/binghatti-flare-assets/binghatti-flare-project-facts.pdf",
      "https://binghatti-public.s3.me-central-1.amazonaws.com/project-assets/binghatti-flare-assets/binghatti-flare-floor-plan.pdf",
      "https://binghatti-public.s3.me-central-1.amazonaws.com/project-assets/binghatti-flare-assets/binghatti-flare-project-location.pdf"
    ],
    "iframes": [
      "https://www.google.com/maps/embed?pb=!1m18!1m12!1m3!1d115554.4861775229!2d55.21706659286809!3d25.166854353886798!2m3!1f0!2f0!3f0!3m2!1i1024!2i768!4f13.1!3m3!1m2!1s0x3e5f69cbe987368d%3A0x29d0ae84c05d3d36!2sBinghatti%20Aquarise!5e0!3m2!1sen!2sae!4v1746546106639!5m2!1sen!2sae",
      "https://www.google.com/maps/embed?pb=!1m18!1m12!1m3!1d231388.7310710296!2d55.04598751442834!3d25.018834826093297!2m3!1f0!2f0!3f0!3m2!1i1024!2i768!4f13.1!3m3!1m2!1s0x3e5f6d6807b6859f%3A0x3863af3088359355!2sBinghatti%20Flare!5e0!3m2!1sen!2sae!4v1753259205317!5m2!1sen!2sae",
      "https://www.youtube.com/embed/DwBk6wGQx88?controls=0&rel=0&autoplay=0&enablejsapi=1"
    ]
  }
}