{
  "slug": "skyscape-aura",
  "developer": "Sobha",
  "community_slug": "",
  "name_en": "Skyscape Aura",
  "name_ar": "Skyscape Aura",
  "website": "",
  "canonical_url": "",
  "logo": "",
  "image_hero": "",
  "images_gallery": [],
  "video_url": "null",
  "tour_3d_url": "",
  "coordinates": {
    "lat": 25.1723744,
    "lng": 55.3295953
  },
  "address_en": "",
  "address_ar": "",
  "status": "under-construction",
  "status_label_en": "",
  "status_label_ar": "",
  "handover_date": "",
  "launch_date": "",
  "property_types": [
    {
      "en": "Apartments",
      "ar": "Apartments"
    }
  ],
  "bedrooms": [
    1,
    2,
    3
  ],
  "units_count": null,
  "area_sqm_min": 71,
  "area_sqm_max": 186,
  "area_sqft_min": 774,
  "area_sqft_max": 2008,
  "price_aed_min": 1780000,
  "price_aed_max": 4920000,
  "price_note_en": "",
  "price_note_ar": "",
  "payment_plan": {
    "on_booking_percent": null,
    "during_construction_percent": null,
    "on_handover_percent": null,
    "post_handover_years": null,
    "installments": []
  },
  "service_charge_aed_sqft": null,
  "amenities": [
    {
      "en": "Infinity Pool",
      "ar": "مسبح إنفينيتي"
    },
    {
      "en": "Wet Deck",
      "ar": "منصة مبللة"
    },
    {
      "en": "Shaded Pool Deck",
      "ar": "منصة مسبح مظللة"
    },
    {
      "en": "Sun Loungers",
      "ar": "كراسي استلقاء للتشمس"
    },
    {
      "en": "Shaded Kids’ Pool Area & Play Area",
      "ar": "منطقة مسبح ولعب مظللة للأطفال"
    },
    {
      "en": "Raised Lawn",
      "ar": "عشب مرتفع"
    },
    {
      "en": "Shaded Communal Areas",
      "ar": "مناطق مشتركة مظللة"
    },
    {
      "en": "BBQ Pods",
      "ar": "أكواخ شواء"
    },
    {
      "en": "Ground-Level Boutiques & Cafes",
      "ar": "بوتيكات ومقاهي على مستوى الأرض"
    },
    {
      "en": "Landscaped Garden",
      "ar": "حديقة طبيعية"
    },
    {
      "en": "[object Object]",
      "ar": ""
    }
  ],
  "features": [],
  "description_en": "Introducing Skyscape Aura, its unveiling heralds sophistication and grandeur. With its sleek design and commanding presence, Skyscape Aura captivates with unparalleled charm. Welcome to the new era where every silhouette is infused with the spirit of architectural excellence.",
  "description_ar": "اكتشف باي فيو من أدريس ريزورتس في إعمار بيتشفرونت، واستمتع بالإطلالات البانورامية والتصميمات الداخلية الفاخرة ووسائل الراحة. تفضل بزيارة موقعنا الإلكتروني للمزيد من المعلومات. تتزين الواجهات المصممة بأناقة بأمواج أثيرية تعكس مياه الخليج العربي المتلألئة. مفردات فاخرة مستوحاة من روعة وسحر دبي، مترجمة بأدق التفاصيل، من الداخل والخارج. مرافق رائعة مستوحاة من براعة إعمار في الحياة الراقية في شقق وبنتهاوس تحمل علامة تجارية، مفروشة بفخامة ومصممة خصيصًا لتلبية احتياجاتك. يحمل منتجع باي فيو من أدريس في إعمار بيتشفرونت المستقبل في تفاصيله ويعد بحياة ستحقق أحلامك بالعيش الفاخر بجانب البحر ورفاهية عصرية لا مثيل لها؛ فرصة فريدة من نوعها للاحتفال بحياة دبي في أكثر المشاريع الساحلية تميزًا في المدينة. البنتهاوس هي الإنجازات المتوجة لحياة غنية ومجزية. تقع في قمة الأبراج المصممة بأناقة، ستجد أعلى مستويات أسلوب حياة إعمار بيتشفرونت. تُعد بنتهاوس باي فيو من أدريس ريزورتس المكونة من 5 غرف نوم مثالاً للحياة الفاخرة في السماء، لوحة من الرفاهية المبهرة على أفق الخليج العربي. أربع وحدات بنتهاوس فريدة تتجاوز كل التوقعات بإطلالات 360 درجة وتصميمات عقارات شاطئية معاصرة. تمتزج أرقى التصميمات الداخلية والمواد بسلاسة مع التصميم الأنيق، لخلق ملاذ للرفاهية المطلقة في الوجهة المطلقة.",
  "brochure_url": "",
  "floorplans": [],
  "masterplan_url": "",
  "price_list_url": "",
  "spec_sheet_url": "",
  "rera_permit_no": "",
  "rera_project_no": "",
  "construction_updates": [],
  "mortgage_available": null,
  "developer_rating": null,
  "tags": [],
  "contact": {
    "phone": null,
    "email": null,
    "whatsapp": null
  },
  "source_urls": [
    "https://sobharealty.com/properties-in-dubai/skyscape-aura/"
  ],
  "seo": {
    "title_en": "",
    "title_ar": "",
    "meta_description_en": "",
    "meta_description_ar": ""
  },
  "created_at": "",
  "updated_at": "2025-11-30T19:55:10.021211Z"
}